greydot/__init__.py
greydot/airtime.py
greydot/b2c.py
greydot/errors.py
greydot/runtest.py
greydot/signup.py
greydot/sms.py
greydot/wallet.py
greydot/tests/__init__.py
greydot/tests/test_airtime.py
greydot/tests/test_b2c.py
greydot/tests/test_signup.py
greydot/tests/test_sms.py
greydot/tests/test_wallet.py
greydot_api-0.8.2.dist-info/LICENSE
greydot_api-0.8.2.dist-info/METADATA
greydot_api-0.8.2.dist-info/WHEEL
greydot_api-0.8.2.dist-info/top_level.txt
greydot_api-0.8.2.dist-info/RECORD
